einops/__init__.py
einops/_backends.py
einops/_torch_specific.py
einops/einops.py
einops/parsing.py
einops/layers/__init__.py
einops/layers/_einmix.py
einops/layers/chainer.py
einops/layers/gluon.py
einops/layers/keras.py
einops/layers/tensorflow.py
einops/layers/torch.py
einops-0.4.0.dist-info/LICENSE
einops-0.4.0.dist-info/METADATA
einops-0.4.0.dist-info/WHEEL
einops-0.4.0.dist-info/top_level.txt
einops-0.4.0.dist-info/RECORD
