Metadata-Version: 2.1
Name: einops
Version: 0.4.0
Summary: A new flavour of deep learning operations
Home-page: https://github.com/arogozhnikov/einops
Author: Alex Rogozhnikov
License: UNKNOWN
Keywords: deep learning,neural networks,tensor manipulation,machine learning,scientific computations,einops
Platform: UNKNOWN
Classifier: Intended Audience :: Science/Research
Classifier: Programming Language :: Python :: 3 
License-File: LICENSE
